{"trans":[{"variable":"appstore_description","locale":"ko-KR","translation":"단어를 거꾸로 말하여 점수를 얻습니다. 말하는 동안 별표 버튼을 길게 누릅니다. 연속으로 많은 단어를 올바르게 맞추면 더 많은 점수를 얻습니다. 점수 승수를 보호하기 위해 방패를 사용합니다. 페널티 없이 새 단어를 얻으려면 건너뛰기를 사용하십시오."},{"variable":"appstore_promotext","locale":"ko-KR","translation":"다른 사람들과 지혜를 시험하고 거꾸로 말하는 기술을 마스터하십시오. 자신을 향상시키고 순위표를 정복하세요!"},{"variable":"iap_bundle_description","locale":"ko-KR","translation":"점수 승수를 보호하는 방패"},{"variable":"iap_bundle_shields_1","locale":"ko-KR","translation":"작은 방패 묶음"},{"variable":"iap_bundle_shields_2","locale":"ko-KR","translation":"중형 방패 묶음"},{"variable":"iap_bundle_shields_3","locale":"ko-KR","translation":"큰 방패 묶음"},{"variable":"iap_bundle_thankYou","locale":"ko-KR","translation":"구매 해주셔서 감사합니다,"},{"variable":"iap_info_failed","locale":"ko-KR","translation":"구매 실패"},{"variable":"iap_restore_purchases","locale":"ko-KR","translation":"구매를 복원"},{"variable":"iap_shop_title","locale":"ko-KR","translation":"가게"}]}