{"trans":[{"variable":"dg_dailytask_done_content","locale":"vi-VN","translation":"Nhiệm vụ hàng ngày đã hoàn thành! Hệ số điểm của bạn bây giờ cao hơn. Hãy chắc chắn hoàn thành các nhiệm vụ vào ngày mai để đạt được hệ số nhân điểm cao hơn nữa."},{"variable":"dg_dailytask_done_title","locale":"vi-VN","translation":"Xin chúc mừng!"},{"variable":"dg_noConnection_content","locale":"vi-VN","translation":"Kết nối hoạt động là cần thiết để tiếp tục chơi."},{"variable":"dg_noConnection_title","locale":"vi-VN","translation":"Không có kết nối"},{"variable":"hud_dailyDone_text","locale":"vi-VN","translation":"Nhiệm vụ hàng ngày đã hoàn thành!"},{"variable":"hud_newTask_text","locale":"vi-VN","translation":"Nhiệm vụ mới"},{"variable":"hud_rank_text","locale":"vi-VN","translation":"Thứ hạng"},{"variable":"hud_sessionScore_text","locale":"vi-VN","translation":"Điểm phiên"},{"variable":"hud_streak_text","locale":"vi-VN","translation":"Vệt hệ số"},{"variable":"lb_month_text","locale":"vi-VN","translation":"Tháng"},{"variable":"lb_week_text","locale":"vi-VN","translation":"Tuần"},{"variable":"lb_year_text","locale":"vi-VN","translation":"Năm"},{"variable":"splash_start_text","locale":"vi-VN","translation":"Bắt đầu trò chơi"}]}