{"Allwords":[{"word":"minä","times_tried":0,"times_skipped":0,"times_right":0,"total_score":0.0,"avg_score":0.0,"tier":0,"set":0},{"word":"hänen","times_tried":0,"times_skipped":0,"times_right":0,"total_score":0.0,"avg_score":0.0,"tier":0,"set":0},{"word":"että","times_tried":0,"times_skipped":0,"times_right":0,"total_score":0.0,"avg_score":0.0,"tier":0,"set":0},{"word":"hän","times_tried":0,"times_skipped":0,"times_right":0,"total_score":0.0,"avg_score":0.0,"tier":0,"set":0},{"word":"päälle","times_tried":0,"times_skipped":0,"times_right":0,"total_score":0.0,"avg_score":0.0,"tier":0,"set":0},{"word":"tämä","times_tried":0,"times_skipped":0,"times_right":0,"total_score":0.0,"avg_score":0.0,"tier":0,"set":0},{"word":"mitä","times_tried":0,"times_skipped":0,"times_right":0,"total_score":0.0,"avg_score":0.0,"tier":0,"set":0},{"word":"päälle","times_tried":0,"times_skipped":0,"times_right":0,"total_score":0.0,"avg_score":0.0,"tier":0,"set":0},{"word":"tehdä","times_tried":0,"times_skipped":0,"times_right":0,"total_score":0.0,"avg_score":0.0,"tier":0,"set":0},{"word":"sisään","times_tried":0,"times_skipped":0,"times_right":0,"total_score":0.0,"avg_score":0.0,"tier":0,"set":0},{"word":"tehdä","times_tried":0,"times_skipped":0,"times_right":0,"total_score":0.0,"avg_score":0.0,"tier":0,"set":0},{"word":"myös","times_tried":0,"times_skipped":0,"times_right":0,"total_score":0.0,"avg_score":0.0,"tier":0,"set":0},{"word":"pää","times_tried":0,"times_skipped":0,"times_right":0,"total_score":0.0,"avg_score":0.0,"tier":0,"set":0},{"word":"käsi","times_tried":0,"times_skipped":0,"times_right":0,"total_score":0.0,"avg_score":0.0,"tier":0,"set":0},{"word":"lisätä","times_tried":0,"times_skipped":0,"times_right":0,"total_score":0.0,"avg_score":0.0,"tier":0,"set":0},{"word":"täällä","times_tried":0,"times_skipped":0,"times_right":0,"total_score":0.0,"avg_score":0.0,"tier":0,"set":0},{"word":"säädös","times_tried":0,"times_skipped":0,"times_right":0,"total_score":0.0,"avg_score":0.0,"tier":0,"set":0},{"word":"kysyä","times_tried":0,"times_skipped":0,"times_right":0,"total_score":0.0,"avg_score":0.0,"tier":0,"set":0},{"word":"yrittää","times_tried":0,"times_skipped":0,"times_right":0,"total_score":0.0,"avg_score":0.0,"tier":0,"set":0},{"word":"jälleen","times_tried":0,"times_skipped":0,"times_right":0,"total_score":0.0,"avg_score":0.0,"tier":0,"set":0},{"word":"eläin","times_tried":0,"times_skipped":0,"times_right":0,"total_score":0.0,"avg_score":0.0,"tier":0,"set":0},{"word":"äiti","times_tried":0,"times_skipped":0,"times_right":0,"total_score":0.0,"avg_score":0.0,"tier":0,"set":0},{"word":"lähellä","times_tried":0,"times_skipped":0,"times_right":0,"total_score":0.0,"avg_score":0.0,"tier":0,"set":0},{"word":"isä","times_tried":0,"times_skipped":0,"times_right":0,"total_score":0.0,"avg_score":0.0,"tier":0,"set":0},{"word":"työ","times_tried":0,"times_skipped":0,"times_right":0,"total_score":0.0,"avg_score":0.0,"tier":0,"set":0},{"word":"elää","times_tried":0,"times_skipped":0,"times_right":0,"total_score":0.0,"avg_score":0.0,"tier":0,"set":0},{"word":"jälkeen","times_tried":0,"times_skipped":0,"times_right":0,"total_score":0.0,"avg_score":0.0,"tier":0,"set":0},{"word":"vähän","times_tried":0,"times_skipped":0,"times_right":0,"total_score":0.0,"avg_score":0.0,"tier":0,"set":0},{"word":"pyöreä","times_tried":0,"times_skipped":0,"times_right":0,"total_score":0.0,"avg_score":0.0,"tier":0,"set":0},{"word":"hyvä","times_tried":0,"times_skipped":0,"times_right":0,"total_score":0.0,"avg_score":0.0,"tier":0,"set":0},{"word":"meidän","times_tried":0,"times_skipped":0,"times_right":0,"total_score":0.0,"avg_score":0.0,"tier":0,"set":0},{"word":"hän","times_tried":0,"times_skipped":0,"times_right":0,"total_score":0.0,"avg_score":0.0,"tier":0,"set":0},{"word":"siellä","times_tried":0,"times_skipped":0,"times_right":0,"total_score":0.0,"avg_score":0.0,"tier":0,"set":0},{"word":"ylös","times_tried":0,"times_skipped":0,"times_right":0,"total_score":0.0,"avg_score":0.0,"tier":0,"set":0},{"word":"käyttää","times_tried":0,"times_skipped":0,"times_right":0,"total_score":0.0,"avg_score":0.0,"tier":0,"set":0},{"word":"niitä","times_tried":0,"times_skipped":0,"times_right":0,"total_score":0.0,"avg_score":0.0,"tier":0,"set":0},{"word":"nämä","times_tried":0,"times_skipped":0,"times_right":0,"total_score":0.0,"avg_score":0.0,"tier":0,"set":0},{"word":"hänen","times_tried":0,"times_skipped":0,"times_right":0,"total_score":0.0,"avg_score":0.0,"tier":0,"set":0},{"word":"pitkä","times_tried":0,"times_skipped":0,"times_right":0,"total_score":0.0,"avg_score":0.0,"tier":0,"set":0},{"word":"tehdä","times_tried":0,"times_skipped":0,"times_right":0,"total_score":0.0,"avg_score":0.0,"tier":0,"set":0},{"word":"nähdä","times_tried":0,"times_skipped":0,"times_right":0,"total_score":0.0,"avg_score":0.0,"tier":0,"set":0},{"word":"häntä","times_tried":0,"times_skipped":0,"times_right":0,"total_score":0.0,"avg_score":0.0,"tier":0,"set":0},{"word":"lisää","times_tried":0,"times_skipped":0,"times_right":0,"total_score":0.0,"avg_score":0.0,"tier":0,"set":0},{"word":"päivä","times_tried":0,"times_skipped":0,"times_right":0,"total_score":0.0,"avg_score":0.0,"tier":0,"set":0},{"word":"mennä","times_tried":0,"times_skipped":0,"times_right":0,"total_score":0.0,"avg_score":0.0,"tier":0,"set":0},{"word":"ääni","times_tried":0,"times_skipped":0,"times_right":0,"total_score":0.0,"avg_score":0.0,"tier":0,"set":0},{"word":"tietää","times_tried":0,"times_skipped":0,"times_right":0,"total_score":0.0,"avg_score":0.0,"tier":0,"set":0},{"word":"ensimmäinen","times_tried":0,"times_skipped":0,"times_right":0,"total_score":0.0,"avg_score":0.0,"tier":0,"set":0},{"word":"löytää","times_tried":0,"times_skipped":0,"times_right":0,"total_score":0.0,"avg_score":0.0,"tier":0,"set":0},{"word":"pää","times_tried":0,"times_skipped":0,"times_right":0,"total_score":0.0,"avg_score":0.0,"tier":0,"set":0},{"word":"seistä","times_tried":0,"times_skipped":0,"times_right":0,"total_score":0.0,"avg_score":0.0,"tier":0,"set":0},{"word":"pitäisi","times_tried":0,"times_skipped":0,"times_right":0,"total_score":0.0,"avg_score":0.0,"tier":0,"set":0},{"word":"löytyi","times_tried":0,"times_skipped":0,"times_right":0,"total_score":0.0,"avg_score":0.0,"tier":0,"set":0},{"word":"vielä","times_tried":0,"times_skipped":0,"times_right":0,"total_score":0.0,"avg_score":0.0,"tier":0,"set":0},{"word":"neljä","times_tried":0,"times_skipped":0,"times_right":0,"total_score":0.0,"avg_score":0.0,"tier":0,"set":0},{"word":"välillä","times_tried":0,"times_skipped":0,"times_right":0,"total_score":0.0,"avg_score":0.0,"tier":0,"set":0},{"word":"pitää","times_tried":0,"times_skipped":0,"times_right":0,"total_score":0.0,"avg_score":0.0,"tier":0,"set":0},{"word":"silmä","times_tried":0,"times_skipped":0,"times_right":0,"total_score":0.0,"avg_score":0.0,"tier":0,"set":0},{"word":"ehkä","times_tried":0,"times_skipped":0,"times_right":0,"total_score":0.0,"avg_score":0.0,"tier":0,"set":0},{"word":"pitkälle","times_tried":0,"times_skipped":0,"times_right":0,"total_score":0.0,"avg_score":0.0,"tier":0,"set":0},{"word":"piirtää","times_tried":0,"times_skipped":0,"times_right":0,"total_score":0.0,"avg_score":0.0,"tier":0,"set":0},{"word":"myöhään","times_tried":0,"times_skipped":0,"times_right":0,"total_score":0.0,"avg_score":0.0,"tier":0,"set":0},{"word":"eivät","times_tried":0,"times_skipped":0,"times_right":0,"total_score":0.0,"avg_score":0.0,"tier":0,"set":0},{"word":"lehdistö","times_tried":0,"times_skipped":0,"times_right":0,"total_score":0.0,"avg_score":0.0,"tier":0,"set":0},{"word":"lähellä","times_tried":0,"times_skipped":0,"times_right":0,"total_score":0.0,"avg_score":0.0,"tier":0,"set":0},{"word":"yö","times_tried":0,"times_skipped":0,"times_right":0,"total_score":0.0,"avg_score":0.0,"tier":0,"set":0},{"word":"elämä","times_tried":0,"times_skipped":0,"times_right":0,"total_score":0.0,"avg_score":0.0,"tier":0,"set":0},{"word":"syödä","times_tried":0,"times_skipped":0,"times_right":0,"total_score":0.0,"avg_score":0.0,"tier":0,"set":0},{"word":"ystävä","times_tried":0,"times_skipped":0,"times_right":0,"total_score":0.0,"avg_score":0.0,"tier":0,"set":0},{"word":"väri","times_tried":0,"times_skipped":0,"times_right":0,"total_score":0.0,"avg_score":0.0,"tier":0,"set":0},{"word":"tärkein","times_tried":0,"times_skipped":0,"times_right":0,"total_score":0.0,"avg_score":0.0,"tier":0,"set":0},{"word":"näyttää","times_tried":0,"times_skipped":0,"times_right":0,"total_score":0.0,"avg_score":0.0,"tier":0,"set":0},{"word":"yhdessä","times_tried":0,"times_skipped":0,"times_right":0,"total_score":0.0,"avg_score":0.0,"tier":0,"set":0},{"word":"kävellä","times_tried":0,"times_skipped":0,"times_right":0,"total_score":0.0,"avg_score":0.0,"tier":0,"set":0},{"word":"ryhmä","times_tried":0,"times_skipped":0,"times_right":0,"total_score":0.0,"avg_score":0.0,"tier":0,"set":0},{"word":"tyttö","times_tried":0,"times_skipped":0,"times_right":0,"total_score":0.0,"avg_score":0.0,"tier":0,"set":0},{"word":"edellä","times_tried":0,"times_skipped":0,"times_right":0,"total_score":0.0,"avg_score":0.0,"tier":0,"set":0},{"word":"jätä","times_tried":0,"times_skipped":0,"times_right":0,"total_score":0.0,"avg_score":0.0,"tier":0,"set":0},{"word":"täydellinen","times_tried":0,"times_skipped":0,"times_right":0,"total_score":0.0,"avg_score":0.0,"tier":0,"set":0},{"word":"järjestys","times_tried":0,"times_skipped":0,"times_right":0,"total_score":0.0,"avg_score":0.0,"tier":0,"set":0},{"word":"etelään","times_tried":0,"times_skipped":0,"times_right":0,"total_score":0.0,"avg_score":0.0,"tier":0,"set":0},{"word":"lisääntyä","times_tried":0,"times_skipped":0,"times_right":0,"total_score":0.0,"avg_score":0.0,"tier":0,"set":0},{"word":"ei mitään","times_tried":0,"times_skipped":0,"times_right":0,"total_score":0.0,"avg_score":0.0,"tier":0,"set":0},{"word":"pysyä","times_tried":0,"times_skipped":0,"times_right":0,"total_score":0.0,"avg_score":0.0,"tier":0,"set":0},{"word":"pyörä","times_tried":0,"times_skipped":0,"times_right":0,"total_score":0.0,"avg_score":0.0,"tier":0,"set":0},{"word":"täysi","times_tried":0,"times_skipped":0,"times_right":0,"total_score":0.0,"avg_score":0.0,"tier":0,"set":0},{"word":"päättää","times_tried":0,"times_skipped":0,"times_right":0,"total_score":0.0,"avg_score":0.0,"tier":0,"set":0},{"word":"syvä","times_tried":0,"times_skipped":0,"times_right":0,"total_score":0.0,"avg_score":0.0,"tier":0,"set":0},{"word":"järjestelmä","times_tried":0,"times_skipped":0,"times_right":0,"total_score":0.0,"avg_score":0.0,"tier":0,"set":0},{"word":"ennätys","times_tried":0,"times_skipped":0,"times_right":0,"total_score":0.0,"avg_score":0.0,"tier":0,"set":0},{"word":"lämpö","times_tried":0,"times_skipped":0,"times_right":0,"total_score":0.0,"avg_score":0.0,"tier":0,"set":0},{"word":"kyllä","times_tried":0,"times_skipped":0,"times_right":0,"total_score":0.0,"avg_score":0.0,"tier":0,"set":0},{"word":"täyttää","times_tried":0,"times_skipped":0,"times_right":0,"total_score":0.0,"avg_score":0.0,"tier":0,"set":0},{"word":"itään","times_tried":0,"times_skipped":0,"times_right":0,"total_score":0.0,"avg_score":0.0,"tier":0,"set":0},{"word":"yksikkö","times_tried":0,"times_skipped":0,"times_right":0,"total_score":0.0,"avg_score":0.0,"tier":0,"set":0},{"word":"lentää","times_tried":0,"times_skipped":0,"times_right":0,"total_score":0.0,"avg_score":0.0,"tier":0,"set":0},{"word":"itkeä","times_tried":0,"times_skipped":0,"times_right":0,"total_score":0.0,"avg_score":0.0,"tier":0,"set":0},{"word":"pimeä","times_tried":0,"times_skipped":0,"times_right":0,"total_score":0.0,"avg_score":0.0,"tier":0,"set":0},{"word":"tähti","times_tried":0,"times_skipped":0,"times_right":0,"total_score":0.0,"avg_score":0.0,"tier":0,"set":0},{"word":"kenttä","times_tried":0,"times_skipped":0,"times_right":0,"total_score":0.0,"avg_score":0.0,"tier":0,"set":0},{"word":"levätä","times_tried":0,"times_skipped":0,"times_right":0,"total_score":0.0,"avg_score":0.0,"tier":0,"set":0},{"word":"sisältävät","times_tried":0,"times_skipped":0,"times_right":0,"total_score":0.0,"avg_score":0.0,"tier":0,"set":0},{"word":"vihreä","times_tried":0,"times_skipped":0,"times_right":0,"total_score":0.0,"avg_score":0.0,"tier":0,"set":0},{"word":"kehittää","times_tried":0,"times_skipped":0,"times_right":0,"total_score":0.0,"avg_score":0.0,"tier":0,"set":0},{"word":"lämmin","times_tried":0,"times_skipped":0,"times_right":0,"total_score":0.0,"avg_score":0.0,"tier":0,"set":0},{"word":"erityistä","times_tried":0,"times_skipped":0,"times_right":0,"total_score":0.0,"avg_score":0.0,"tier":0,"set":0},{"word":"selkeä","times_tried":0,"times_skipped":0,"times_right":0,"total_score":0.0,"avg_score":0.0,"tier":0,"set":0},{"word":"pyrstö","times_tried":0,"times_skipped":0,"times_right":0,"total_score":0.0,"avg_score":0.0,"tier":0,"set":0},{"word":"pidä","times_tried":0,"times_skipped":0,"times_right":0,"total_score":0.0,"avg_score":0.0,"tier":0,"set":0},{"word":"länsi","times_tried":0,"times_skipped":0,"times_right":0,"total_score":0.0,"avg_score":0.0,"tier":0,"set":0},{"word":"vähemmän","times_tried":0,"times_skipped":0,"times_right":0,"total_score":0.0,"avg_score":0.0,"tier":0,"set":0},{"word":"henkilö","times_tried":0,"times_skipped":0,"times_right":0,"total_score":0.0,"avg_score":0.0,"tier":0,"set":0},{"word":"ilmestyä","times_tried":0,"times_skipped":0,"times_right":0,"total_score":0.0,"avg_score":0.0,"tier":0,"set":0},{"word":"sääntö","times_tried":0,"times_skipped":0,"times_right":0,"total_score":0.0,"avg_score":0.0,"tier":0,"set":0},{"word":"säätelevät","times_tried":0,"times_skipped":0,"times_right":0,"total_score":0.0,"avg_score":0.0,"tier":0,"set":0},{"word":"vetää","times_tried":0,"times_skipped":0,"times_right":0,"total_score":0.0,"avg_score":0.0,"tier":0,"set":0},{"word":"kylmä","times_tried":0,"times_skipped":0,"times_right":0,"total_score":0.0,"avg_score":0.0,"tier":0,"set":0},{"word":"ääni","times_tried":0,"times_skipped":0,"times_right":0,"total_score":0.0,"avg_score":0.0,"tier":0,"set":0},{"word":"metsästää","times_tried":0,"times_skipped":0,"times_right":0,"total_score":0.0,"avg_score":0.0,"tier":0,"set":0},{"word":"todennäköinen","times_tried":0,"times_skipped":0,"times_right":0,"total_score":0.0,"avg_score":0.0,"tier":0,"set":0},{"word":"sängyssä","times_tried":0,"times_skipped":0,"times_right":0,"total_score":0.0,"avg_score":0.0,"tier":0,"set":0},{"word":"ehkä","times_tried":0,"times_skipped":0,"times_right":0,"total_score":0.0,"avg_score":0.0,"tier":0,"set":0},{"word":"äkillinen","times_tried":0,"times_skipped":0,"times_right":0,"total_score":0.0,"avg_score":0.0,"tier":0,"set":0},{"word":"neliö","times_tried":0,"times_skipped":0,"times_right":0,"total_score":0.0,"avg_score":0.0,"tier":0,"set":0},{"word":"jää","times_tried":0,"times_skipped":0,"times_right":0,"total_score":0.0,"avg_score":0.0,"tier":0,"set":0},{"word":"ympyrä","times_tried":0,"times_skipped":0,"times_right":0,"total_score":0.0,"avg_score":0.0,"tier":0,"set":0},{"word":"sisältävät","times_tried":0,"times_skipped":0,"times_right":0,"total_score":0.0,"avg_score":0.0,"tier":0,"set":0},{"word":"vielä","times_tried":0,"times_skipped":0,"times_right":0,"total_score":0.0,"avg_score":0.0,"tier":0,"set":0},{"word":"sydän","times_tried":0,"times_skipped":0,"times_right":0,"total_score":0.0,"avg_score":0.0,"tier":0,"set":0},{"word":"leveä","times_tried":0,"times_skipped":0,"times_right":0,"total_score":0.0,"avg_score":0.0,"tier":0,"set":0},{"word":"metsä","times_tried":0,"times_skipped":0,"times_right":0,"total_score":0.0,"avg_score":0.0,"tier":0,"set":0},{"word":"myymälä","times_tried":0,"times_skipped":0,"times_right":0,"total_score":0.0,"avg_score":0.0,"tier":0,"set":0},{"word":"kesä","times_tried":0,"times_skipped":0,"times_right":0,"total_score":0.0,"avg_score":0.0,"tier":0,"set":0},{"word":"yksinäinen","times_tried":0,"times_skipped":0,"times_right":0,"total_score":0.0,"avg_score":0.0,"tier":0,"set":0},{"word":"seinä","times_tried":0,"times_skipped":0,"times_right":0,"total_score":0.0,"avg_score":0.0,"tier":0,"set":0},{"word":"väline","times_tried":0,"times_skipped":0,"times_right":0,"total_score":0.0,"avg_score":0.0,"tier":0,"set":0},{"word":"säilytettävä","times_tried":0,"times_skipped":0,"times_right":0,"total_score":0.0,"avg_score":0.0,"tier":0,"set":0},{"word":"lehmä","times_tried":0,"times_skipped":0,"times_right":0,"total_score":0.0,"avg_score":0.0,"tier":0,"set":0},{"word":"työ","times_tried":0,"times_skipped":0,"times_right":0,"total_score":0.0,"avg_score":0.0,"tier":0,"set":0},{"word":"pehmeä","times_tried":0,"times_skipped":0,"times_right":0,"total_score":0.0,"avg_score":0.0,"tier":0,"set":0},{"word":"sää","times_tried":0,"times_skipped":0,"times_right":0,"total_score":0.0,"avg_score":0.0,"tier":0,"set":0},{"word":"vähiten","times_tried":0,"times_skipped":0,"times_right":0,"total_score":0.0,"avg_score":0.0,"tier":0,"set":0},{"word":"sävy","times_tried":0,"times_skipped":0,"times_right":0,"total_score":0.0,"avg_score":0.0,"tier":0,"set":0},{"word":"yhtyä","times_tried":0,"times_skipped":0,"times_right":0,"total_score":0.0,"avg_score":0.0,"tier":0,"set":0},{"word":"öljy","times_tried":0,"times_skipped":0,"times_right":0,"total_score":0.0,"avg_score":0.0,"tier":0,"set":0},{"word":"yhtäläinen","times_tried":0,"times_skipped":0,"times_right":0,"total_score":0.0,"avg_score":0.0,"tier":0,"set":0},{"word":"lähetetty","times_tried":0,"times_skipped":0,"times_right":0,"total_score":0.0,"avg_score":0.0,"tier":0,"set":0},{"word":"kerätä","times_tried":0,"times_skipped":0,"times_right":0,"total_score":0.0,"avg_score":0.0,"tier":0,"set":0},{"word":"keskellä","times_tried":0,"times_skipped":0,"times_right":0,"total_score":0.0,"avg_score":0.0,"tier":0,"set":0},{"word":"järvi","times_tried":0,"times_skipped":0,"times_right":0,"total_score":0.0,"avg_score":0.0,"tier":0,"set":0},{"word":"äänekäs","times_tried":0,"times_skipped":0,"times_right":0,"total_score":0.0,"avg_score":0.0,"tier":0,"set":0},{"word":"kevät","times_tried":0,"times_skipped":0,"times_right":0,"total_score":0.0,"avg_score":0.0,"tier":0,"set":0},{"word":"menetelmä","times_tried":0,"times_skipped":0,"times_right":0,"total_score":0.0,"avg_score":0.0,"tier":0,"set":0},{"word":"ikä","times_tried":0,"times_skipped":0,"times_right":0,"total_score":0.0,"avg_score":0.0,"tier":0,"set":0},{"word":"yllätys","times_tried":0,"times_skipped":0,"times_right":0,"total_score":0.0,"avg_score":0.0,"tier":0,"set":0},{"word":"kiivetä","times_tried":0,"times_skipped":0,"times_right":0,"total_score":0.0,"avg_score":0.0,"tier":0,"set":0},{"word":"viileä","times_tried":0,"times_skipped":0,"times_right":0,"total_score":0.0,"avg_score":0.0,"tier":0,"set":0},{"word":"kaksikymmentä","times_tried":0,"times_skipped":0,"times_right":0,"total_score":0.0,"avg_score":0.0,"tier":0,"set":0},{"word":"prässi","times_tried":0,"times_skipped":0,"times_right":0,"total_score":0.0,"avg_score":0.0,"tier":0,"set":0},{"word":"reikä","times_tried":0,"times_skipped":0,"times_right":0,"total_score":0.0,"avg_score":0.0,"tier":0,"set":0},{"word":"kylä","times_tried":0,"times_skipped":0,"times_right":0,"total_score":0.0,"avg_score":0.0,"tier":0,"set":0},{"word":"seitsemän","times_tried":0,"times_skipped":0,"times_right":0,"total_score":0.0,"avg_score":0.0,"tier":0,"set":0},{"word":"mäki","times_tried":0,"times_skipped":0,"times_right":0,"total_score":0.0,"avg_score":0.0,"tier":0,"set":0},{"word":"pitkä","times_tried":0,"times_skipped":0,"times_right":0,"total_score":0.0,"avg_score":0.0,"tier":0,"set":0},{"word":"maaperä","times_tried":0,"times_skipped":0,"times_right":0,"total_score":0.0,"avg_score":0.0,"tier":0,"set":0},{"word":"lämpötila","times_tried":0,"times_skipped":0,"times_right":0,"total_score":0.0,"avg_score":0.0,"tier":0,"set":0},{"word":"näkymä","times_tried":0,"times_skipped":0,"times_right":0,"total_score":0.0,"avg_score":0.0,"tier":0,"set":0},{"word":"merkityksessä","times_tried":0,"times_skipped":0,"times_right":0,"total_score":0.0,"avg_score":0.0,"tier":0,"set":0},{"word":"pääoma","times_tried":0,"times_skipped":0,"times_right":0,"total_score":0.0,"avg_score":0.0,"tier":0,"set":0},{"word":"eivät","times_tried":0,"times_skipped":0,"times_right":0,"total_score":0.0,"avg_score":0.0,"tier":0,"set":0},{"word":"hedelmät","times_tried":0,"times_skipped":0,"times_right":0,"total_score":0.0,"avg_score":0.0,"tier":0,"set":0},{"word":"käytäntö","times_tried":0,"times_skipped":0,"times_right":0,"total_score":0.0,"avg_score":0.0,"tier":0,"set":0},{"word":"lääkäri","times_tried":0,"times_skipped":0,"times_right":0,"total_score":0.0,"avg_score":0.0,"tier":0,"set":0},{"word":"olkaa hyvä","times_tried":0,"times_skipped":0,"times_right":0,"total_score":0.0,"avg_score":0.0,"tier":0,"set":0},{"word":"keskipäivällä","times_tried":0,"times_skipped":0,"times_right":0,"total_score":0.0,"avg_score":0.0,"tier":0,"set":0},{"word":"hyönteinen","times_tried":0,"times_skipped":0,"times_right":0,"total_score":0.0,"avg_score":0.0,"tier":0,"set":0},{"word":"sähköinen","times_tried":0,"times_skipped":0,"times_right":0,"total_score":0.0,"avg_score":0.0,"tier":0,"set":0},{"word":"näin","times_tried":0,"times_skipped":0,"times_right":0,"total_score":0.0,"avg_score":0.0,"tier":0,"set":0},{"word":"lempeä","times_tried":0,"times_skipped":0,"times_right":0,"total_score":0.0,"avg_score":0.0,"tier":0,"set":0},{"word":"välttämätön","times_tried":0,"times_skipped":0,"times_right":0,"total_score":0.0,"avg_score":0.0,"tier":0,"set":0},{"word":"teräviä","times_tried":0,"times_skipped":0,"times_right":0,"total_score":0.0,"avg_score":0.0,"tier":0,"set":0},{"word":"väkijoukko","times_tried":0,"times_skipped":0,"times_right":0,"total_score":0.0,"avg_score":0.0,"tier":0,"set":0},{"word":"näky","times_tried":0,"times_skipped":0,"times_right":0,"total_score":0.0,"avg_score":0.0,"tier":0,"set":0},{"word":"päällikkö","times_tried":0,"times_skipped":0,"times_right":0,"total_score":0.0,"avg_score":0.0,"tier":0,"set":0},{"word":"merkittävä","times_tried":0,"times_skipped":0,"times_right":0,"total_score":0.0,"avg_score":0.0,"tier":0,"set":0},{"word":"lähettää","times_tried":0,"times_skipped":0,"times_right":0,"total_score":0.0,"avg_score":0.0,"tier":0,"set":0},{"word":"kytkeä","times_tried":0,"times_skipped":0,"times_right":0,"total_score":0.0,"avg_score":0.0,"tier":0,"set":0},{"word":"viettää","times_tried":0,"times_skipped":0,"times_right":0,"total_score":0.0,"avg_score":0.0,"tier":0,"set":0},{"word":"alkuperäinen","times_tried":0,"times_skipped":0,"times_right":0,"total_score":0.0,"avg_score":0.0,"tier":0,"set":0},{"word":"isä","times_tried":0,"times_skipped":0,"times_right":0,"total_score":0.0,"avg_score":0.0,"tier":0,"set":0},{"word":"leipä","times_tried":0,"times_skipped":0,"times_right":0,"total_score":0.0,"avg_score":0.0,"tier":0,"set":0},{"word":"välitön","times_tried":0,"times_skipped":0,"times_right":0,"total_score":0.0,"avg_score":0.0,"tier":0,"set":0},{"word":"esiintyä","times_tried":0,"times_skipped":0,"times_right":0,"total_score":0.0,"avg_score":0.0,"tier":0,"set":0},{"word":"höyry","times_tried":0,"times_skipped":0,"times_right":0,"total_score":0.0,"avg_score":0.0,"tier":0,"set":0},{"word":"osamäärä","times_tried":0,"times_skipped":0,"times_right":0,"total_score":0.0,"avg_score":0.0,"tier":0,"set":0},{"word":"pääte","times_tried":0,"times_skipped":0,"times_right":0,"total_score":0.0,"avg_score":0.0,"tier":0,"set":0},{"word":"teräs","times_tried":0,"times_skipped":0,"times_right":0,"total_score":0.0,"avg_score":0.0,"tier":0,"set":0},{"word":"eteenpäin","times_tried":0,"times_skipped":0,"times_right":0,"total_score":0.0,"avg_score":0.0,"tier":0,"set":0},{"word":"bändi","times_tried":0,"times_skipped":0,"times_right":0,"total_score":0.0,"avg_score":0.0,"tier":0,"set":0},{"word":"köysi","times_tried":0,"times_skipped":0,"times_right":0,"total_score":0.0,"avg_score":0.0,"tier":0,"set":0},{"word":"työkalu","times_tried":0,"times_skipped":0,"times_right":0,"total_score":0.0,"avg_score":0.0,"tier":0,"set":0},{"word":"yhteensä","times_tried":0,"times_skipped":0,"times_right":0,"total_score":0.0,"avg_score":0.0,"tier":0,"set":0},{"word":"eikä myöskään","times_tried":0,"times_skipped":0,"times_right":0,"total_score":0.0,"avg_score":0.0,"tier":0,"set":0},{"word":"myydä","times_tried":0,"times_skipped":0,"times_right":0,"total_score":0.0,"avg_score":0.0,"tier":0,"set":0},{"word":"vähentää","times_tried":0,"times_skipped":0,"times_right":0,"total_score":0.0,"avg_score":0.0,"tier":0,"set":0},{"word":"päinvastainen","times_tried":0,"times_skipped":0,"times_right":0,"total_score":0.0,"avg_score":0.0,"tier":0,"set":0},{"word":"kenkä","times_tried":0,"times_skipped":0,"times_right":0,"total_score":0.0,"avg_score":0.0,"tier":0,"set":0},{"word":"olkapää","times_tried":0,"times_skipped":0,"times_right":0,"total_score":0.0,"avg_score":0.0,"tier":0,"set":0},{"word":"leviäminen","times_tried":0,"times_skipped":0,"times_right":0,"total_score":0.0,"avg_score":0.0,"tier":0,"set":0},{"word":"järjestää","times_tried":0,"times_skipped":0,"times_right":0,"total_score":0.0,"avg_score":0.0,"tier":0,"set":0},{"word":"keksiä","times_tried":0,"times_skipped":0,"times_right":0,"total_score":0.0,"avg_score":0.0,"tier":0,"set":0},{"word":"määrittää","times_tried":0,"times_skipped":0,"times_right":0,"total_score":0.0,"avg_score":0.0,"tier":0,"set":0},{"word":"yhdeksän","times_tried":0,"times_skipped":0,"times_right":0,"total_score":0.0,"avg_score":0.0,"tier":0,"set":0},{"word":"kerätä","times_tried":0,"times_skipped":0,"times_right":0,"total_score":0.0,"avg_score":0.0,"tier":0,"set":0},{"word":"venyttää","times_tried":0,"times_skipped":0,"times_right":0,"total_score":0.0,"avg_score":0.0,"tier":0,"set":0},{"word":"heittää","times_tried":0,"times_skipped":0,"times_right":0,"total_score":0.0,"avg_score":0.0,"tier":0,"set":0},{"word":"väärä","times_tried":0,"times_skipped":0,"times_right":0,"total_score":0.0,"avg_score":0.0,"tier":0,"set":0},{"word":"nenä","times_tried":0,"times_skipped":0,"times_right":0,"total_score":0.0,"avg_score":0.0,"tier":0,"set":0}]}